MANIFEST.in
README.rst
setup.cfg
setup.py
analytics/__init__.py
analytics/admin.py
analytics/models.py
analytics/migrations/0001_initial.py
analytics/migrations/__init__.py
analytics/templates/google_analytics/analytics.html
analytics/templatetags/__init__.py
analytics/templatetags/googleanalytics.py
django_google_analytics.egg-info/PKG-INFO
django_google_analytics.egg-info/SOURCES.txt
django_google_analytics.egg-info/dependency_links.txt
django_google_analytics.egg-info/entry_points.txt
django_google_analytics.egg-info/not-zip-safe
django_google_analytics.egg-info/top_level.txt