Metadata-Version: 1.0
Name: django-google-analytics
Version: 2
Summary: Google analytics web property per site in django admin
Home-page: wilburweb.com
Author: Benjamin Wilbur
Author-email: wilburb@wilburweb.com
License: GNU General Public License
Keywords: django google analytics site
Platform: UNKNOWN
